numpy3/Astar.py
numpy3/BFS.py
numpy3/DFID.py
numpy3/DFS.py
numpy3/DFS2.py
numpy3/Genetic.py
numpy3/Hill_Climbing.py
numpy3/Simulated_Annealing.py
numpy3/UCS.py
numpy3/__init__.py
numpy3-0.2.dist-info/METADATA
numpy3-0.2.dist-info/WHEEL
numpy3-0.2.dist-info/top_level.txt
numpy3-0.2.dist-info/RECORD
