Metadata-Version: 2.1
Name: numpy3
Version: 0.2
Summary: A package for doing cool stuff
Home-page: UNKNOWN
Author: Your Name
Author-email: your@email.com
License: UNKNOWN
Platform: UNKNOWN
